loguwant/__init__.py
loguwant/logger.py
loguwant-0.0.1.dist-info/LICENSE
loguwant-0.0.1.dist-info/METADATA
loguwant-0.0.1.dist-info/WHEEL
loguwant-0.0.1.dist-info/top_level.txt
loguwant-0.0.1.dist-info/RECORD
