Metadata-Version: 2.1
Name: loguwant
Version: 0.0.1
Summary: It is a Python package that enables you to log only what you want.
Home-page: https://github.com/yashgoyal07/loguwant
Author: Yash Goyal
Author-email: yashgoyalcs@gmail.com
License: UNKNOWN
Project-URL: Bug Tracker, https://github.com/yashgoyal07/loguwant/issues
Platform: UNKNOWN
Classifier: Programming Language :: Python :: 3
Classifier: License :: OSI Approved :: MIT License
Classifier: Operating System :: OS Independent
Requires-Python: >=3.6
License-File: LICENSE
